setup.cfg
setup.py
MultiAgentKit/__init__.py
MultiAgentKit.egg-info/PKG-INFO
MultiAgentKit.egg-info/SOURCES.txt
MultiAgentKit.egg-info/dependency_links.txt
MultiAgentKit.egg-info/requires.txt
MultiAgentKit.egg-info/top_level.txt
MultiAgentKit/Agent/Agent.py
MultiAgentKit/Agent/DFAgent.py
MultiAgentKit/Agent/__init__.py
MultiAgentKit/Behaviours/Base.py
MultiAgentKit/Behaviours/Communication.py
MultiAgentKit/Behaviours/Driver.py
MultiAgentKit/Behaviours/Listening.py
MultiAgentKit/Behaviours/__init__.py
MultiAgentKit/System/MAS.py
MultiAgentKit/utilities/Common_Protocol.py
MultiAgentKit/utilities/TCPClient.py
MultiAgentKit/utilities/TCPServer.py
MultiAgentKit/utilities/__init__.py
MultiAgentKit/utilities/tool.py