Metadata-Version: 2.1
Name: MultiAgentKit
Version: 1.3.3
Summary: 修复DF查询为空的情况！
Home-page: https://github.com/not_define/please_wait
Author: lidongdong
Author-email: 927052521@qq.com
License: MIT Licence
Keywords: pip,licensetool,gm,license,tool
Platform: any
